pynyaata/__init__.py
pynyaata/config.py
pynyaata/flarerequests.py
pynyaata/forms.py
pynyaata/models.py
pynyaata/utils.py
pynyaata/connectors/__init__.py
pynyaata/connectors/animeultime.py
pynyaata/connectors/core.py
pynyaata/connectors/nyaa.py
pynyaata/connectors/yggtorrent.py
pynyaata/static/css/bulma-prefers-dark.css.map
pynyaata/static/css/bulma-prefers-dark.min.css
pynyaata/static/css/bulma-tooltip.min.css
pynyaata/static/css/bulma.css.map
pynyaata/static/css/bulma.min.css
pynyaata/static/css/font-awesome.css.map
pynyaata/static/css/font-awesome.min.css
pynyaata/static/css/styles.css
pynyaata/static/favicons/animeultime.png
pynyaata/static/favicons/blank.png
pynyaata/static/favicons/favicon.ico
pynyaata/static/favicons/nyaa.png
pynyaata/static/favicons/pantsu.png
pynyaata/static/favicons/yggtorrent.png
pynyaata/static/fonts/FontAwesome.otf
pynyaata/static/fonts/fontawesome-webfont.eot
pynyaata/static/fonts/fontawesome-webfont.svg
pynyaata/static/fonts/fontawesome-webfont.ttf
pynyaata/static/fonts/fontawesome-webfont.woff
pynyaata/static/fonts/fontawesome-webfont.woff2
pynyaata/templates/latest.html
pynyaata/templates/layout.html
pynyaata/templates/list.html
pynyaata/templates/search.html
pynyaata/templates/admin/edit.html
pynyaata/templates/admin/list.html
pynyaata/templates/admin/folder/edit.html
pynyaata/templates/admin/folder/list.html
PyNyaaTa-202306260752.dist-info/LICENSE.txt
PyNyaaTa-202306260752.dist-info/METADATA
PyNyaaTa-202306260752.dist-info/WHEEL
PyNyaaTa-202306260752.dist-info/entry_points.txt
PyNyaaTa-202306260752.dist-info/top_level.txt
PyNyaaTa-202306260752.dist-info/RECORD
