Metadata-Version: 2.1
Name: PyNyaaTa
Version: 202306260752
Summary: π 😼た, Xéfir's personal animes torrent search engine
Home-page: https://git.crystalyx.net/Xefir/PyNyaaTa
Author: Xéfir Destiny
Author-email: xefir@crystalyx.net
Classifier: Programming Language :: Python :: 3
Classifier: Operating System :: OS Independent
Requires-Python: >=3.5
License-File: LICENSE.txt
Requires-Dist: Flask (==2.3.2)
Requires-Dist: Flask-SQLAlchemy (==2.5.1)
Requires-Dist: Flask-HTTPAuth (==4.8.0)
Requires-Dist: Flask-WTF (==1.1.1)
Requires-Dist: WTForms (==2.3.3)
Requires-Dist: PyMySQL (==1.1.0)
Requires-Dist: pg8000 (==1.29.8)
Requires-Dist: requests (==2.31.0)
Requires-Dist: charset-normalizer (==3.1.0)
Requires-Dist: beautifulsoup4 (==4.12.2)
Requires-Dist: python-dotenv (==1.0.0)
Requires-Dist: dateparser (==1.1.8)
Requires-Dist: redis (==4.6.0)
Requires-Dist: transmission-rpc (==3.4.2)
